agenthub/README.md
agenthub/__init__.py
agenthub_py-0.1.1.dist-info/METADATA
agenthub_py-0.1.1.dist-info/WHEEL
agenthub_py-0.1.1.dist-info/top_level.txt
agenthub_py-0.1.1.dist-info/RECORD
