Metadata-Version: 2.4
Name: agenthub-py
Version: 0.1.1
Summary: A framework for building and running AI agents
Home-page: https://agenthublabs.com
Author: Youssef Kallel
Author-email: Youssef Kallel <youssef@agenthublabs.com>
License: MIT
Project-URL: Homepage, https://www.agenthublabs.com/
Project-URL: Documentation, https://www.agenthublabs.com/docs
Keywords: ai,agents,framework
Classifier: Development Status :: 3 - Alpha
Classifier: Intended Audience :: Developers
Classifier: Topic :: Software Development :: Libraries :: Python Modules
Classifier: License :: OSI Approved :: MIT License
Classifier: Programming Language :: Python :: 3
Classifier: Programming Language :: Python :: 3.8
Classifier: Programming Language :: Python :: 3.9
Classifier: Programming Language :: Python :: 3.10
Classifier: Programming Language :: Python :: 3.11
Classifier: Programming Language :: Python :: 3.12
Classifier: Programming Language :: Python :: 3.13
Requires-Python: >=3.8
Dynamic: author
Dynamic: home-page
Dynamic: requires-python
